
    [
        {"key":"Büyükorhan","value":"Büyükorhan"},
        {"key":"Gemlik","value":"Gemlik"},
        {"key":"Gürsu","value":"Gürsu"},
        {"key":"Harmancık","value":"Harmancık"},
        {"key":"İnegöl","value":"İnegöl"},
        {"key":"İznik","value":"İznik"},
        {"key":"Karacabey","value":"Karacabey"},
        {"key":"Keles","value":"Keles"},
        {"key":"Kestel","value":"Kestel"},
        {"key":"Mudanya","value":"Mudanya"},
        {"key":"MustafaKemalPaşa","value":"MustafaKemalPaşa"},
        {"key":"Nilüfer","value":"Nilüfer"},
        {"key":"Orhaneli","value":"Orhaneli"},
        {"key":"Orhangazi","value":"Orhangazi"},
        {"key":"Osmangazi","value":"Osmangazi"},
        {"key":"Yıldırım","value":"Yenişehir"},
        {"key":"Yıldırım","value":"Yıldırım"}
        
    ]

